[{"name":"No Poverty","node_type":"Goal"},{"name":"No Hunger","node_type":"Goal"},{"name":"Good Health and Well-Being","node_type":"Goal"},{"name":"Quality Education","node_type":"Goal"},{"name":"Gender Equality","node_type":"Goal"},{"name":"Clean Water and Sanitation","node_type":"Goal"},{"name":"Affordable and Clean Energy","node_type":"Goal"},{"name":"Decent Work and Economic Growth","node_type":"Goal"},{"name":"Industry, Innovation and Infrastrucure","node_type":"Goal"},{"name":"Reduced Inequalities","node_type":"Goal"},{"name":"Sustainable Cities and Communities","node_type":"Goal"},{"name":"Responsible Consumption and Production","node_type":"Goal"},{"name":"Climate Action","node_type":"Goal"},{"name":"Life Below Water","node_type":"Goal"},{"name":"Life on Land","node_type":"Goal"},{"name":"Peace, Justice and Strong Institutions","node_type":"Goal"},{"name":"Partnership for the Goals","node_type":"Goal"},{"name":"annotation","node_type":"Task"},{"name":"annotation methods","node_type":"Method"},{"name":"attention","node_type":"Method"},{"name":"automatic speech recognition","node_type":"Task"},{"name":"automatic speech recognition models","node_type":"Method"},{"name":"bert","node_type":"Method"},{"name":"classification","node_type":"Task"},{"name":"classifiers","node_type":"Method"},{"name":"conditional random field","node_type":"Method"},{"name":"convolutional neural network","node_type":"Method"},{"name":"coreference resolution","node_type":"Task"},{"name":"covid 19","node_type":"Task"},{"name":"deep neural network","node_type":"Method"},{"name":"domain adaption","node_type":"Method"},{"name":"ensemble methods","node_type":"Method"},{"name":"event extraction","node_type":"Task"},{"name":"fact checking","node_type":"Task"},{"name":"fact checking models","node_type":"Method"},{"name":"fake news detection","node_type":"Task"},{"name":"hate speech","node_type":"Task"},{"name":"hope speech detection","node_type":"Task"},{"name":"hybrid approach","node_type":"Method"},{"name":"inference","node_type":"Task"},{"name":"information retrieval","node_type":"Task"},{"name":"language models","node_type":"Method"},{"name":"language technology","node_type":"Method"},{"name":"lstm","node_type":"Method"},{"name":"machine learning methods","node_type":"Method"},{"name":"machine translation","node_type":"Task"},{"name":"named entity recognition","node_type":"Task"},{"name":"natural language generation","node_type":"Task"},{"name":"ner models","node_type":"Method"},{"name":"nlp applications","node_type":"Task"},{"name":"nlp models","node_type":"Method"},{"name":"parsing","node_type":"Task"},{"name":"part of speech","node_type":"Task"},{"name":"part of speech models","node_type":"Method"},{"name":"question answering","node_type":"Task"},{"name":"recurrent neural networks","node_type":"Method"},{"name":"relation extraction","node_type":"Task"},{"name":"roberta","node_type":"Method"},{"name":"rumor detection","node_type":"Task"},{"name":"sentiment analysis","node_type":"Task"},{"name":"stance detection","node_type":"Task"},{"name":"text summarization","node_type":"Task"},{"name":"topic models","node_type":"Method"},{"name":"toxic spans detection","node_type":"Task"},{"name":"transfer learning","node_type":"Method"},{"name":"transformers","node_type":"Method"},{"name":"word embeddings","node_type":"Method"},{"name":"Other methods","node_type":"Method"},{"name":"Other tasks","node_type":"Task"}]