{"No Poverty": 0, "Zero Hunger": 1, "Good Health And Well-Being": 2, "Quality Education": 3, "Gender Equality": 4, "Clean Water And Sanitation": 5, "Decent Work And Economic Growth": 6, "Industry, Innovation And Infrastructure": 7, "Reduced Inequalities": 8, "Sustainable Cities And Communities": 9, "Responsible Consumption And Production": 10, "Climate Action": 11, "Life Below Water": 12, "Life On Land": 13, "Peace, Justice And Strong Institutions": 14, "Partnership For The Goals": 15, "Annotation Schemes": 16, "Automatic Speech Recognition": 17, "BERT": 18, "COVID 19": 19, "Classification": 20, "Classifiers": 21, "Computational Linguistics": 22, "Computational Models": 23, "Conditional Random Field": 24, "Convolutional Neural Network": 25, "Data Collection": 26, "Deep Neural Network": 27, "Downstream Task": 28, "Ensemble Methods": 29, "Event Extraction": 30, "Fact Checking": 31, "Fake News Detection": 32, "Gender Bias Mitigation": 33, "Healthcare": 34, "Inference": 35, "Information Extraction": 36, "Information Retrieval": 37, "LSTM": 38, "Language Models": 39, "Language Technology": 40, "Machine Learning Methods": 41, "Machine Translation": 42, "Machine Translation System": 43, "Multi Task Learning": 44, "NLP Applications": 45, "NLP Models": 46, "Named Entity Recognition": 47, "Natural Language Generation": 48, "Neural Models": 49, "Neural Network": 50, "Predictions": 51, "Question Answering": 52, "Recurrent Neural Networks": 53, "Relation Extraction": 54, "RoBERTa": 55, "Sentiment Analysis": 56, "Stance Detection": 57, "Supervised Learning": 58, "Support Vector Machine": 59, "Text Summarization": 60, "Topic Models": 61, "Toxicity Detection": 62, "Transfer Learning": 63, "Transformers": 64, "Word Embeddings": 65, "Affordable And Clean Energy": 66, "Other Methods": 67, "Other Tasks": 68}