[{"source":"No Poverty","id_source":"0","target":"covid 19","id_target":"18","weight":1.0,"id_order":0},{"source":"No Poverty","id_source":"0","target":"hate speech detection","id_target":"19","weight":3.5,"id_order":0},{"source":"No Poverty","id_source":"0","target":"hope speech detection","id_target":"20","weight":4.7,"id_order":0},{"source":"No Poverty","id_source":"0","target":"machine translation","id_target":"21","weight":27.8,"id_order":0},{"source":"No Poverty","id_source":"0","target":"named entity recognition","id_target":"22","weight":4.2,"id_order":0},{"source":"No Poverty","id_source":"0","target":"nlp tasks","id_target":"23","weight":3.0,"id_order":0},{"source":"No Poverty","id_source":"0","target":"offensive language identification","id_target":"24","weight":0.2,"id_order":0},{"source":"No Poverty","id_source":"0","target":"parsing","id_target":"25","weight":5.0,"id_order":0},{"source":"No Poverty","id_source":"0","target":"sentiment analysis","id_target":"26","weight":4.0,"id_order":0},{"source":"No Poverty","id_source":"0","target":"summarization","id_target":"27","weight":1.3,"id_order":0},{"source":"No Poverty","id_source":"0","target":"text classification","id_target":"28","weight":1.5,"id_order":0},{"source":"No Poverty","id_source":"0","target":"classification","id_target":"29","weight":1.6,"id_order":0},{"source":"No Poverty","id_source":"0","target":"automatic speech recognition","id_target":"30","weight":2.8,"id_order":0},{"source":"No Hunger","id_source":"1","target":"machine translation","id_target":"21","weight":6.7,"id_order":0},{"source":"No Hunger","id_source":"1","target":"summarization","id_target":"27","weight":0.8,"id_order":0},{"source":"No Hunger","id_source":"1","target":"text classification","id_target":"28","weight":1.0,"id_order":0},{"source":"No Hunger","id_source":"1","target":"classification","id_target":"29","weight":0.2,"id_order":0},{"source":"No Hunger","id_source":"1","target":"annotation","id_target":"32","weight":0.5,"id_order":0},{"source":"Good Health and Well-Being","id_source":"2","target":"covid 19","id_target":"18","weight":5.2,"id_order":0},{"source":"Good Health and Well-Being","id_source":"2","target":"hope speech detection","id_target":"20","weight":0.3,"id_order":0},{"source":"Good Health and Well-Being","id_source":"2","target":"machine translation","id_target":"21","weight":4.0,"id_order":0},{"source":"Good Health and Well-Being","id_source":"2","target":"named entity recognition","id_target":"22","weight":1.8,"id_order":0},{"source":"Good Health and Well-Being","id_source":"2","target":"parsing","id_target":"25","weight":2.5,"id_order":0},{"source":"Good Health and Well-Being","id_source":"2","target":"sentiment analysis","id_target":"26","weight":1.5,"id_order":0},{"source":"Good Health and Well-Being","id_source":"2","target":"summarization","id_target":"27","weight":8.1,"id_order":0},{"source":"Good Health and Well-Being","id_source":"2","target":"text classification","id_target":"28","weight":0.7,"id_order":0},{"source":"Good Health and Well-Being","id_source":"2","target":"classification","id_target":"29","weight":9.9,"id_order":0},{"source":"Good Health and Well-Being","id_source":"2","target":"automatic speech recognition","id_target":"30","weight":1.3,"id_order":0},{"source":"Good Health and Well-Being","id_source":"2","target":"annotation","id_target":"32","weight":1.8,"id_order":0},{"source":"Good Health and Well-Being","id_source":"2","target":"emotion detection","id_target":"33","weight":0.5,"id_order":0},{"source":"Good Health and Well-Being","id_source":"2","target":"fake news detection","id_target":"34","weight":0.5,"id_order":0},{"source":"Good Health and Well-Being","id_source":"2","target":"question answering","id_target":"35","weight":6.4,"id_order":0},{"source":"Good Health and Well-Being","id_source":"2","target":"relation extraction","id_target":"36","weight":0.8,"id_order":0},{"source":"Quality Education","id_source":"3","target":"machine translation","id_target":"21","weight":30.9,"id_order":0},{"source":"Quality Education","id_source":"3","target":"named entity recognition","id_target":"22","weight":5.1,"id_order":0},{"source":"Quality Education","id_source":"3","target":"nlp tasks","id_target":"23","weight":2.0,"id_order":0},{"source":"Quality Education","id_source":"3","target":"sentiment analysis","id_target":"26","weight":1.0,"id_order":0},{"source":"Quality Education","id_source":"3","target":"summarization","id_target":"27","weight":1.9,"id_order":0},{"source":"Quality Education","id_source":"3","target":"text classification","id_target":"28","weight":1.0,"id_order":0},{"source":"Quality Education","id_source":"3","target":"classification","id_target":"29","weight":2.0,"id_order":0},{"source":"Quality Education","id_source":"3","target":"automatic speech recognition","id_target":"30","weight":0.5,"id_order":0},{"source":"Quality Education","id_source":"3","target":"fake news detection","id_target":"34","weight":1.5,"id_order":0},{"source":"Quality Education","id_source":"3","target":"question answering","id_target":"35","weight":6.5,"id_order":0},{"source":"Quality Education","id_source":"3","target":"relation extraction","id_target":"36","weight":2.2,"id_order":0},{"source":"Quality Education","id_source":"3","target":"offensive language detection","id_target":"37","weight":0.5,"id_order":0},{"source":"Gender Equality","id_source":"4","target":"covid 19","id_target":"18","weight":0.2,"id_order":0},{"source":"Gender Equality","id_source":"4","target":"hate speech detection","id_target":"19","weight":7.8,"id_order":0},{"source":"Gender Equality","id_source":"4","target":"hope speech detection","id_target":"20","weight":16.8,"id_order":0},{"source":"Gender Equality","id_source":"4","target":"machine translation","id_target":"21","weight":194.3,"id_order":0},{"source":"Gender Equality","id_source":"4","target":"named entity recognition","id_target":"22","weight":30.7,"id_order":0},{"source":"Gender Equality","id_source":"4","target":"nlp tasks","id_target":"23","weight":6.0,"id_order":0},{"source":"Gender Equality","id_source":"4","target":"offensive language identification","id_target":"24","weight":1.5,"id_order":0},{"source":"Gender Equality","id_source":"4","target":"parsing","id_target":"25","weight":6.3,"id_order":0},{"source":"Gender Equality","id_source":"4","target":"sentiment analysis","id_target":"26","weight":8.9,"id_order":0},{"source":"Gender Equality","id_source":"4","target":"summarization","id_target":"27","weight":7.0,"id_order":0},{"source":"Gender Equality","id_source":"4","target":"text classification","id_target":"28","weight":5.0,"id_order":0},{"source":"Gender Equality","id_source":"4","target":"classification","id_target":"29","weight":17.5,"id_order":0},{"source":"Gender Equality","id_source":"4","target":"automatic speech recognition","id_target":"30","weight":8.4,"id_order":0},{"source":"Gender Equality","id_source":"4","target":"annotation","id_target":"32","weight":4.8,"id_order":0},{"source":"Gender Equality","id_source":"4","target":"emotion detection","id_target":"33","weight":7.2,"id_order":0},{"source":"Gender Equality","id_source":"4","target":"question answering","id_target":"35","weight":3.3,"id_order":0},{"source":"Gender Equality","id_source":"4","target":"relation extraction","id_target":"36","weight":1.2,"id_order":0},{"source":"Gender Equality","id_source":"4","target":"offensive language detection","id_target":"37","weight":0.8,"id_order":0},{"source":"Gender Equality","id_source":"4","target":"emotion recognition","id_target":"38","weight":4.9,"id_order":0},{"source":"Clean Water and Sanitation","id_source":"5","target":"machine translation","id_target":"21","weight":9.7,"id_order":0},{"source":"Clean Water and Sanitation","id_source":"5","target":"named entity recognition","id_target":"22","weight":3.8,"id_order":0},{"source":"Clean Water and Sanitation","id_source":"5","target":"offensive language identification","id_target":"24","weight":0.5,"id_order":0},{"source":"Clean Water and Sanitation","id_source":"5","target":"parsing","id_target":"25","weight":0.5,"id_order":0},{"source":"Clean Water and Sanitation","id_source":"5","target":"sentiment analysis","id_target":"26","weight":0.2,"id_order":0},{"source":"Clean Water and Sanitation","id_source":"5","target":"summarization","id_target":"27","weight":1.0,"id_order":0},{"source":"Clean Water and Sanitation","id_source":"5","target":"classification","id_target":"29","weight":1.0,"id_order":0},{"source":"Clean Water and Sanitation","id_source":"5","target":"annotation","id_target":"32","weight":2.2,"id_order":0},{"source":"Clean Water and Sanitation","id_source":"5","target":"question answering","id_target":"35","weight":1.1,"id_order":0},{"source":"Clean Water and Sanitation","id_source":"5","target":"relation extraction","id_target":"36","weight":1.2,"id_order":0},{"source":"Affordable and Clean Energy","id_source":"6","target":"machine translation","id_target":"21","weight":2.4,"id_order":0},{"source":"Affordable and Clean Energy","id_source":"6","target":"question answering","id_target":"35","weight":1.0,"id_order":0},{"source":"Decent Work and Economic Growth","id_source":"7","target":"machine translation","id_target":"21","weight":13.1,"id_order":0},{"source":"Decent Work and Economic Growth","id_source":"7","target":"nlp tasks","id_target":"23","weight":1.0,"id_order":0},{"source":"Decent Work and Economic Growth","id_source":"7","target":"sentiment analysis","id_target":"26","weight":1.3,"id_order":0},{"source":"Decent Work and Economic Growth","id_source":"7","target":"classification","id_target":"29","weight":2.0,"id_order":0},{"source":"Industry, Innovation and Infrastrucure","id_source":"8","target":"machine translation","id_target":"21","weight":4.7,"id_order":0},{"source":"Industry, Innovation and Infrastrucure","id_source":"8","target":"offensive language identification","id_target":"24","weight":0.8,"id_order":0},{"source":"Industry, Innovation and Infrastrucure","id_source":"8","target":"parsing","id_target":"25","weight":0.5,"id_order":0},{"source":"Industry, Innovation and Infrastrucure","id_source":"8","target":"sentiment analysis","id_target":"26","weight":3.8,"id_order":0},{"source":"Industry, Innovation and Infrastrucure","id_source":"8","target":"classification","id_target":"29","weight":0.7,"id_order":0},{"source":"Industry, Innovation and Infrastrucure","id_source":"8","target":"automatic speech recognition","id_target":"30","weight":1.8,"id_order":0},{"source":"Industry, Innovation and Infrastrucure","id_source":"8","target":"emotion recognition","id_target":"38","weight":1.5,"id_order":0},{"source":"Reduced Inequalities","id_source":"9","target":"hate speech detection","id_target":"19","weight":4.7,"id_order":0},{"source":"Reduced Inequalities","id_source":"9","target":"machine translation","id_target":"21","weight":13.8,"id_order":0},{"source":"Reduced Inequalities","id_source":"9","target":"named entity recognition","id_target":"22","weight":2.3,"id_order":0},{"source":"Reduced Inequalities","id_source":"9","target":"nlp tasks","id_target":"23","weight":1.0,"id_order":0},{"source":"Reduced Inequalities","id_source":"9","target":"offensive language identification","id_target":"24","weight":7.2,"id_order":0},{"source":"Reduced Inequalities","id_source":"9","target":"parsing","id_target":"25","weight":1.7,"id_order":0},{"source":"Reduced Inequalities","id_source":"9","target":"sentiment analysis","id_target":"26","weight":16.4,"id_order":0},{"source":"Reduced Inequalities","id_source":"9","target":"summarization","id_target":"27","weight":3.1,"id_order":0},{"source":"Reduced Inequalities","id_source":"9","target":"text classification","id_target":"28","weight":2.4,"id_order":0},{"source":"Reduced Inequalities","id_source":"9","target":"classification","id_target":"29","weight":18.0,"id_order":0},{"source":"Reduced Inequalities","id_source":"9","target":"automatic speech recognition","id_target":"30","weight":2.0,"id_order":0},{"source":"Reduced Inequalities","id_source":"9","target":"annotation","id_target":"32","weight":4.0,"id_order":0},{"source":"Reduced Inequalities","id_source":"9","target":"emotion detection","id_target":"33","weight":9.7,"id_order":0},{"source":"Reduced Inequalities","id_source":"9","target":"relation extraction","id_target":"36","weight":3.6,"id_order":0},{"source":"Reduced Inequalities","id_source":"9","target":"offensive language detection","id_target":"37","weight":5.2,"id_order":0},{"source":"Reduced Inequalities","id_source":"9","target":"emotion recognition","id_target":"38","weight":0.4,"id_order":0},{"source":"Sustainable Cities and Communities","id_source":"10","target":"covid 19","id_target":"18","weight":3.0,"id_order":0},{"source":"Sustainable Cities and Communities","id_source":"10","target":"hate speech detection","id_target":"19","weight":1.3,"id_order":0},{"source":"Sustainable Cities and Communities","id_source":"10","target":"machine translation","id_target":"21","weight":15.6,"id_order":0},{"source":"Sustainable Cities and Communities","id_source":"10","target":"named entity recognition","id_target":"22","weight":1.2,"id_order":0},{"source":"Sustainable Cities and Communities","id_source":"10","target":"nlp tasks","id_target":"23","weight":1.0,"id_order":0},{"source":"Sustainable Cities and Communities","id_source":"10","target":"parsing","id_target":"25","weight":0.5,"id_order":0},{"source":"Sustainable Cities and Communities","id_source":"10","target":"sentiment analysis","id_target":"26","weight":4.8,"id_order":0},{"source":"Sustainable Cities and Communities","id_source":"10","target":"summarization","id_target":"27","weight":4.8,"id_order":0},{"source":"Sustainable Cities and Communities","id_source":"10","target":"text classification","id_target":"28","weight":2.2,"id_order":0},{"source":"Sustainable Cities and Communities","id_source":"10","target":"classification","id_target":"29","weight":9.5,"id_order":0},{"source":"Sustainable Cities and Communities","id_source":"10","target":"automatic speech recognition","id_target":"30","weight":4.5,"id_order":0},{"source":"Sustainable Cities and Communities","id_source":"10","target":"annotation","id_target":"32","weight":3.8,"id_order":0},{"source":"Sustainable Cities and Communities","id_source":"10","target":"emotion detection","id_target":"33","weight":0.7,"id_order":0},{"source":"Sustainable Cities and Communities","id_source":"10","target":"emotion recognition","id_target":"38","weight":2.0,"id_order":0},{"source":"Responsible Consumption and Production","id_source":"11","target":"machine translation","id_target":"21","weight":3.5,"id_order":0},{"source":"Responsible Consumption and Production","id_source":"11","target":"automatic speech recognition","id_target":"30","weight":1.8,"id_order":0},{"source":"Responsible Consumption and Production","id_source":"11","target":"question answering","id_target":"35","weight":0.3,"id_order":0},{"source":"Responsible Consumption and Production","id_source":"11","target":"emotion recognition","id_target":"38","weight":1.0,"id_order":0},{"source":"Climate Action","id_source":"12","target":"covid 19","id_target":"18","weight":48.9,"id_order":0},{"source":"Climate Action","id_source":"12","target":"hate speech detection","id_target":"19","weight":3.8,"id_order":0},{"source":"Climate Action","id_source":"12","target":"machine translation","id_target":"21","weight":4.3,"id_order":0},{"source":"Climate Action","id_source":"12","target":"named entity recognition","id_target":"22","weight":7.9,"id_order":0},{"source":"Climate Action","id_source":"12","target":"nlp tasks","id_target":"23","weight":5.0,"id_order":0},{"source":"Climate Action","id_source":"12","target":"offensive language identification","id_target":"24","weight":17.1,"id_order":0},{"source":"Climate Action","id_source":"12","target":"parsing","id_target":"25","weight":2.0,"id_order":0},{"source":"Climate Action","id_source":"12","target":"sentiment analysis","id_target":"26","weight":6.3,"id_order":0},{"source":"Climate Action","id_source":"12","target":"summarization","id_target":"27","weight":4.0,"id_order":0},{"source":"Climate Action","id_source":"12","target":"text classification","id_target":"28","weight":10.1,"id_order":0},{"source":"Climate Action","id_source":"12","target":"classification","id_target":"29","weight":26.8,"id_order":0},{"source":"Climate Action","id_source":"12","target":"automatic speech recognition","id_target":"30","weight":0.6,"id_order":0},{"source":"Climate Action","id_source":"12","target":"annotation","id_target":"32","weight":5.0,"id_order":0},{"source":"Climate Action","id_source":"12","target":"emotion detection","id_target":"33","weight":4.8,"id_order":0},{"source":"Climate Action","id_source":"12","target":"fake news detection","id_target":"34","weight":18.9,"id_order":0},{"source":"Climate Action","id_source":"12","target":"question answering","id_target":"35","weight":1.7,"id_order":0},{"source":"Climate Action","id_source":"12","target":"relation extraction","id_target":"36","weight":2.0,"id_order":0},{"source":"Climate Action","id_source":"12","target":"offensive language detection","id_target":"37","weight":12.9,"id_order":0},{"source":"Climate Action","id_source":"12","target":"emotion recognition","id_target":"38","weight":3.3,"id_order":0},{"source":"Life Below Water","id_source":"13","target":"hope speech detection","id_target":"20","weight":0.5,"id_order":0},{"source":"Life Below Water","id_source":"13","target":"machine translation","id_target":"21","weight":7.3,"id_order":0},{"source":"Life Below Water","id_source":"13","target":"named entity recognition","id_target":"22","weight":9.4,"id_order":0},{"source":"Life Below Water","id_source":"13","target":"offensive language identification","id_target":"24","weight":1.9,"id_order":0},{"source":"Life Below Water","id_source":"13","target":"sentiment analysis","id_target":"26","weight":1.2,"id_order":0},{"source":"Life Below Water","id_source":"13","target":"text classification","id_target":"28","weight":2.2,"id_order":0},{"source":"Life Below Water","id_source":"13","target":"classification","id_target":"29","weight":4.2,"id_order":0},{"source":"Life Below Water","id_source":"13","target":"automatic speech recognition","id_target":"30","weight":4.4,"id_order":0},{"source":"Life Below Water","id_source":"13","target":"annotation","id_target":"32","weight":5.0,"id_order":0},{"source":"Life Below Water","id_source":"13","target":"emotion detection","id_target":"33","weight":2.5,"id_order":0},{"source":"Life Below Water","id_source":"13","target":"question answering","id_target":"35","weight":0.7,"id_order":0},{"source":"Life Below Water","id_source":"13","target":"relation extraction","id_target":"36","weight":0.8,"id_order":0},{"source":"Life Below Water","id_source":"13","target":"emotion recognition","id_target":"38","weight":10.0,"id_order":0},{"source":"Life on Land","id_source":"14","target":"covid 19","id_target":"18","weight":3.0,"id_order":0},{"source":"Life on Land","id_source":"14","target":"machine translation","id_target":"21","weight":5.2,"id_order":0},{"source":"Life on Land","id_source":"14","target":"named entity recognition","id_target":"22","weight":18.4,"id_order":0},{"source":"Life on Land","id_source":"14","target":"nlp tasks","id_target":"23","weight":1.0,"id_order":0},{"source":"Life on Land","id_source":"14","target":"parsing","id_target":"25","weight":5.4,"id_order":0},{"source":"Life on Land","id_source":"14","target":"sentiment analysis","id_target":"26","weight":0.3,"id_order":0},{"source":"Life on Land","id_source":"14","target":"summarization","id_target":"27","weight":0.4,"id_order":0},{"source":"Life on Land","id_source":"14","target":"text classification","id_target":"28","weight":2.6,"id_order":0},{"source":"Life on Land","id_source":"14","target":"classification","id_target":"29","weight":5.6,"id_order":0},{"source":"Life on Land","id_source":"14","target":"automatic speech recognition","id_target":"30","weight":3.1,"id_order":0},{"source":"Life on Land","id_source":"14","target":"annotation","id_target":"32","weight":13.6,"id_order":0},{"source":"Life on Land","id_source":"14","target":"question answering","id_target":"35","weight":2.9,"id_order":0},{"source":"Life on Land","id_source":"14","target":"relation extraction","id_target":"36","weight":1.4,"id_order":0},{"source":"Life on Land","id_source":"14","target":"emotion recognition","id_target":"38","weight":0.8,"id_order":0},{"source":"Peace, Justice and Strong Institutions","id_source":"15","target":"hate speech detection","id_target":"19","weight":4.9,"id_order":0},{"source":"Peace, Justice and Strong Institutions","id_source":"15","target":"machine translation","id_target":"21","weight":12.4,"id_order":0},{"source":"Peace, Justice and Strong Institutions","id_source":"15","target":"named entity recognition","id_target":"22","weight":7.0,"id_order":0},{"source":"Peace, Justice and Strong Institutions","id_source":"15","target":"nlp tasks","id_target":"23","weight":2.0,"id_order":0},{"source":"Peace, Justice and Strong Institutions","id_source":"15","target":"offensive language identification","id_target":"24","weight":1.0,"id_order":0},{"source":"Peace, Justice and Strong Institutions","id_source":"15","target":"parsing","id_target":"25","weight":0.2,"id_order":0},{"source":"Peace, Justice and Strong Institutions","id_source":"15","target":"sentiment analysis","id_target":"26","weight":1.0,"id_order":0},{"source":"Peace, Justice and Strong Institutions","id_source":"15","target":"summarization","id_target":"27","weight":3.8,"id_order":0},{"source":"Peace, Justice and Strong Institutions","id_source":"15","target":"text classification","id_target":"28","weight":1.5,"id_order":0},{"source":"Peace, Justice and Strong Institutions","id_source":"15","target":"classification","id_target":"29","weight":2.1,"id_order":0},{"source":"Peace, Justice and Strong Institutions","id_source":"15","target":"automatic speech recognition","id_target":"30","weight":1.2,"id_order":0},{"source":"Peace, Justice and Strong Institutions","id_source":"15","target":"annotation","id_target":"32","weight":2.5,"id_order":0},{"source":"Peace, Justice and Strong Institutions","id_source":"15","target":"emotion detection","id_target":"33","weight":1.0,"id_order":0},{"source":"Peace, Justice and Strong Institutions","id_source":"15","target":"fake news detection","id_target":"34","weight":1.5,"id_order":0},{"source":"Peace, Justice and Strong Institutions","id_source":"15","target":"question answering","id_target":"35","weight":1.5,"id_order":0},{"source":"Peace, Justice and Strong Institutions","id_source":"15","target":"relation extraction","id_target":"36","weight":2.5,"id_order":0},{"source":"Peace, Justice and Strong Institutions","id_source":"15","target":"offensive language detection","id_target":"37","weight":1.5,"id_order":0},{"source":"Peace, Justice and Strong Institutions","id_source":"15","target":"emotion recognition","id_target":"38","weight":0.3,"id_order":0},{"source":"Partnership for the Goals","id_source":"16","target":"covid 19","id_target":"18","weight":0.5,"id_order":0},{"source":"Partnership for the Goals","id_source":"16","target":"machine translation","id_target":"21","weight":11.9,"id_order":0},{"source":"Partnership for the Goals","id_source":"16","target":"named entity recognition","id_target":"22","weight":10.4,"id_order":0},{"source":"Partnership for the Goals","id_source":"16","target":"parsing","id_target":"25","weight":4.9,"id_order":0},{"source":"Partnership for the Goals","id_source":"16","target":"summarization","id_target":"27","weight":14.1,"id_order":0},{"source":"Partnership for the Goals","id_source":"16","target":"text classification","id_target":"28","weight":0.5,"id_order":0},{"source":"Partnership for the Goals","id_source":"16","target":"classification","id_target":"29","weight":1.1,"id_order":0},{"source":"Partnership for the Goals","id_source":"16","target":"automatic speech recognition","id_target":"30","weight":1.5,"id_order":0},{"source":"Partnership for the Goals","id_source":"16","target":"annotation","id_target":"32","weight":7.5,"id_order":0},{"source":"Partnership for the Goals","id_source":"16","target":"emotion detection","id_target":"33","weight":0.8,"id_order":0},{"source":"Partnership for the Goals","id_source":"16","target":"relation extraction","id_target":"36","weight":5.6,"id_order":0},{"source":"Partnership for the Goals","id_source":"16","target":"emotion recognition","id_target":"38","weight":0.3,"id_order":0},{"source":"Other","id_source":"17","target":"machine translation","id_target":"21","weight":1.0,"id_order":0},{"source":"Other","id_source":"17","target":"named entity recognition","id_target":"22","weight":2.0,"id_order":0},{"source":"Other","id_source":"17","target":"summarization","id_target":"27","weight":0.5,"id_order":0},{"source":"Other","id_source":"17","target":"text classification","id_target":"28","weight":0.5,"id_order":0},{"source":"Other","id_source":"17","target":"classification","id_target":"29","weight":1.5,"id_order":0},{"source":"Other","id_source":"17","target":"annotation","id_target":"32","weight":1.0,"id_order":0},{"source":"Other","id_source":"17","target":"relation extraction","id_target":"36","weight":1.8,"id_order":0},{"source":"covid 19","id_source":"18","target":"roberta","id_target":"40","weight":0.2,"id_order":0},{"source":"covid 19","id_source":"18","target":"transformer","id_target":"41","weight":3.4,"id_order":0},{"source":"covid 19","id_source":"18","target":"bert","id_target":"42","weight":2.7,"id_order":0},{"source":"covid 19","id_source":"18","target":"topic modeling","id_target":"49","weight":1.0,"id_order":0},{"source":"covid 19","id_source":"18","target":"machine learning","id_target":"50","weight":1.0,"id_order":0},{"source":"covid 19","id_source":"18","target":"deep learning","id_target":"52","weight":0.3,"id_order":0},{"source":"covid 19","id_source":"18","target":"word embeddings","id_target":"58","weight":1.0,"id_order":0},{"source":"hate speech detection","id_source":"19","target":"roberta","id_target":"40","weight":0.2,"id_order":0},{"source":"hate speech detection","id_source":"19","target":"transformer","id_target":"41","weight":0.4,"id_order":0},{"source":"hate speech detection","id_source":"19","target":"bert","id_target":"42","weight":2.0,"id_order":0},{"source":"hate speech detection","id_source":"19","target":"ensemble approach","id_target":"59","weight":0.5,"id_order":0},{"source":"hope speech detection","id_source":"20","target":"transformer","id_target":"41","weight":3.0,"id_order":0},{"source":"hope speech detection","id_source":"20","target":"bert","id_target":"42","weight":1.5,"id_order":0},{"source":"hope speech detection","id_source":"20","target":"machine learning","id_target":"50","weight":1.0,"id_order":0},{"source":"hope speech detection","id_source":"20","target":"ensemble approach","id_target":"59","weight":0.5,"id_order":0},{"source":"machine translation","id_source":"21","target":"transformer","id_target":"41","weight":16.2,"id_order":0},{"source":"machine translation","id_source":"21","target":"bert","id_target":"42","weight":0.2,"id_order":0},{"source":"machine translation","id_source":"21","target":"transfer learning","id_target":"43","weight":4.5,"id_order":0},{"source":"machine translation","id_source":"21","target":"human language technologies","id_target":"47","weight":0.2,"id_order":0},{"source":"machine translation","id_source":"21","target":"hybrid approach","id_target":"48","weight":1.2,"id_order":0},{"source":"machine translation","id_source":"21","target":"domain adaptation","id_target":"51","weight":1.7,"id_order":0},{"source":"machine translation","id_source":"21","target":"classifier","id_target":"55","weight":0.7,"id_order":0},{"source":"machine translation","id_source":"21","target":"word embeddings","id_target":"58","weight":1.0,"id_order":0},{"source":"named entity recognition","id_source":"22","target":"transformer","id_target":"41","weight":1.6,"id_order":0},{"source":"named entity recognition","id_source":"22","target":"bert","id_target":"42","weight":3.6,"id_order":0},{"source":"named entity recognition","id_source":"22","target":"transfer learning","id_target":"43","weight":0.6,"id_order":0},{"source":"named entity recognition","id_source":"22","target":"conditional random fields","id_target":"45","weight":1.5,"id_order":0},{"source":"named entity recognition","id_source":"22","target":"hybrid approach","id_target":"48","weight":0.1,"id_order":0},{"source":"named entity recognition","id_source":"22","target":"domain adaptation","id_target":"51","weight":0.7,"id_order":0},{"source":"named entity recognition","id_source":"22","target":"lstm","id_target":"57","weight":1.9,"id_order":0},{"source":"named entity recognition","id_source":"22","target":"word embeddings","id_target":"58","weight":0.2,"id_order":0},{"source":"named entity recognition","id_source":"22","target":"ensemble approach","id_target":"59","weight":0.1,"id_order":0},{"source":"nlp tasks","id_source":"23","target":"transformer","id_target":"41","weight":1.0,"id_order":0},{"source":"nlp tasks","id_source":"23","target":"bert","id_target":"42","weight":1.7,"id_order":0},{"source":"nlp tasks","id_source":"23","target":"transfer learning","id_target":"43","weight":1.0,"id_order":0},{"source":"offensive language identification","id_source":"24","target":"transformer","id_target":"41","weight":3.5,"id_order":0},{"source":"offensive language identification","id_source":"24","target":"bert","id_target":"42","weight":3.2,"id_order":0},{"source":"offensive language identification","id_source":"24","target":"transfer learning","id_target":"43","weight":0.5,"id_order":0},{"source":"offensive language identification","id_source":"24","target":"ensemble approach","id_target":"59","weight":0.3,"id_order":0},{"source":"parsing","id_source":"25","target":"word embeddings","id_target":"58","weight":0.2,"id_order":0},{"source":"sentiment analysis","id_source":"26","target":"transformer","id_target":"41","weight":1.8,"id_order":0},{"source":"sentiment analysis","id_source":"26","target":"bert","id_target":"42","weight":0.3,"id_order":0},{"source":"sentiment analysis","id_source":"26","target":"transfer learning","id_target":"43","weight":0.6,"id_order":0},{"source":"sentiment analysis","id_source":"26","target":"hybrid approach","id_target":"48","weight":1.0,"id_order":0},{"source":"sentiment analysis","id_source":"26","target":"domain adaptation","id_target":"51","weight":1.0,"id_order":0},{"source":"sentiment analysis","id_source":"26","target":"deep learning","id_target":"52","weight":1.0,"id_order":0},{"source":"sentiment analysis","id_source":"26","target":"classifiers","id_target":"53","weight":0.5,"id_order":0},{"source":"sentiment analysis","id_source":"26","target":"annotation scheme","id_target":"54","weight":0.5,"id_order":0},{"source":"summarization","id_source":"27","target":"transformer","id_target":"41","weight":1.8,"id_order":0},{"source":"summarization","id_source":"27","target":"bert","id_target":"42","weight":1.0,"id_order":0},{"source":"summarization","id_source":"27","target":"neural networks","id_target":"46","weight":0.5,"id_order":0},{"source":"summarization","id_source":"27","target":"hybrid approach","id_target":"48","weight":1.0,"id_order":0},{"source":"text classification","id_source":"28","target":"roberta","id_target":"40","weight":0.2,"id_order":0},{"source":"text classification","id_source":"28","target":"transformer","id_target":"41","weight":0.4,"id_order":0},{"source":"text classification","id_source":"28","target":"bert","id_target":"42","weight":2.0,"id_order":0},{"source":"text classification","id_source":"28","target":"domain adaptation","id_target":"51","weight":0.5,"id_order":0},{"source":"text classification","id_source":"28","target":"classifier","id_target":"55","weight":0.7,"id_order":0},{"source":"text classification","id_source":"28","target":"word embeddings","id_target":"58","weight":0.2,"id_order":0},{"source":"classification","id_source":"29","target":"roberta","id_target":"40","weight":0.8,"id_order":0},{"source":"classification","id_source":"29","target":"transformer","id_target":"41","weight":2.3,"id_order":0},{"source":"classification","id_source":"29","target":"bert","id_target":"42","weight":4.8,"id_order":0},{"source":"classification","id_source":"29","target":"transfer learning","id_target":"43","weight":0.5,"id_order":0},{"source":"classification","id_source":"29","target":"neural networks","id_target":"46","weight":0.2,"id_order":0},{"source":"classification","id_source":"29","target":"topic modeling","id_target":"49","weight":1.5,"id_order":0},{"source":"classification","id_source":"29","target":"machine learning","id_target":"50","weight":0.5,"id_order":0},{"source":"classification","id_source":"29","target":"domain adaptation","id_target":"51","weight":1.0,"id_order":0},{"source":"classification","id_source":"29","target":"deep learning","id_target":"52","weight":0.5,"id_order":0},{"source":"classification","id_source":"29","target":"classifiers","id_target":"53","weight":1.0,"id_order":0},{"source":"classification","id_source":"29","target":"lstm","id_target":"57","weight":0.5,"id_order":0},{"source":"automatic speech recognition","id_source":"30","target":"transformer","id_target":"41","weight":1.7,"id_order":0},{"source":"automatic speech recognition","id_source":"30","target":"transfer learning","id_target":"43","weight":0.3,"id_order":0},{"source":"automatic speech recognition","id_source":"30","target":"conditional random fields","id_target":"45","weight":1.0,"id_order":0},{"source":"annotation","id_source":"32","target":"roberta","id_target":"40","weight":1.0,"id_order":0},{"source":"annotation","id_source":"32","target":"bert","id_target":"42","weight":0.2,"id_order":0},{"source":"annotation","id_source":"32","target":"pos","id_target":"44","weight":0.2,"id_order":0},{"source":"annotation","id_source":"32","target":"annotation scheme","id_target":"54","weight":1.0,"id_order":0},{"source":"annotation","id_source":"32","target":"language technologies","id_target":"56","weight":1.0,"id_order":0},{"source":"emotion detection","id_source":"33","target":"transformer","id_target":"41","weight":2.1,"id_order":0},{"source":"emotion detection","id_source":"33","target":"bert","id_target":"42","weight":0.6,"id_order":0},{"source":"emotion detection","id_source":"33","target":"lstm","id_target":"57","weight":0.2,"id_order":0},{"source":"fake news detection","id_source":"34","target":"transformer","id_target":"41","weight":0.2,"id_order":0},{"source":"fake news detection","id_source":"34","target":"bert","id_target":"42","weight":0.3,"id_order":0},{"source":"fake news detection","id_source":"34","target":"transfer learning","id_target":"43","weight":0.5,"id_order":0},{"source":"fake news detection","id_source":"34","target":"deep learning","id_target":"52","weight":0.5,"id_order":0},{"source":"question answering","id_source":"35","target":"transformer","id_target":"41","weight":0.7,"id_order":0},{"source":"question answering","id_source":"35","target":"bert","id_target":"42","weight":0.4,"id_order":0},{"source":"question answering","id_source":"35","target":"human language technologies","id_target":"47","weight":1.0,"id_order":0},{"source":"question answering","id_source":"35","target":"hybrid approach","id_target":"48","weight":0.3,"id_order":0},{"source":"question answering","id_source":"35","target":"ensemble approach","id_target":"59","weight":0.2,"id_order":0},{"source":"relation extraction","id_source":"36","target":"transformer","id_target":"41","weight":0.5,"id_order":0},{"source":"relation extraction","id_source":"36","target":"bert","id_target":"42","weight":1.2,"id_order":0},{"source":"relation extraction","id_source":"36","target":"ensemble approach","id_target":"59","weight":0.3,"id_order":0},{"source":"offensive language detection","id_source":"37","target":"transformer","id_target":"41","weight":1.5,"id_order":0},{"source":"offensive language detection","id_source":"37","target":"bert","id_target":"42","weight":0.4,"id_order":0},{"source":"offensive language detection","id_source":"37","target":"transfer learning","id_target":"43","weight":0.5,"id_order":0},{"source":"offensive language detection","id_source":"37","target":"ensemble approach","id_target":"59","weight":0.3,"id_order":0},{"source":"emotion recognition","id_source":"38","target":"transformer","id_target":"41","weight":0.5,"id_order":0},{"source":"Other tasks","id_source":"9997","target":"roberta","id_target":"40","weight":11.2,"id_order":0},{"source":"Other tasks","id_source":"9997","target":"transformer","id_target":"41","weight":163.0,"id_order":0},{"source":"Other tasks","id_source":"9997","target":"bert","id_target":"42","weight":129.4,"id_order":0},{"source":"Other tasks","id_source":"9997","target":"transfer learning","id_target":"43","weight":23.7,"id_order":0},{"source":"Other tasks","id_source":"9997","target":"pos","id_target":"44","weight":13.2,"id_order":0},{"source":"Other tasks","id_source":"9997","target":"conditional random fields","id_target":"45","weight":10.5,"id_order":0},{"source":"Other tasks","id_source":"9997","target":"neural networks","id_target":"46","weight":11.2,"id_order":0},{"source":"Other tasks","id_source":"9997","target":"human language technologies","id_target":"47","weight":16.8,"id_order":0},{"source":"Other tasks","id_source":"9997","target":"hybrid approach","id_target":"48","weight":9.3,"id_order":0},{"source":"Other tasks","id_source":"9997","target":"topic modeling","id_target":"49","weight":14.5,"id_order":0},{"source":"Other tasks","id_source":"9997","target":"machine learning","id_target":"50","weight":17.5,"id_order":0},{"source":"Other tasks","id_source":"9997","target":"domain adaptation","id_target":"51","weight":9.5,"id_order":0},{"source":"Other tasks","id_source":"9997","target":"deep learning","id_target":"52","weight":17.7,"id_order":0},{"source":"Other tasks","id_source":"9997","target":"classifiers","id_target":"53","weight":9.5,"id_order":0},{"source":"Other tasks","id_source":"9997","target":"annotation scheme","id_target":"54","weight":20.5,"id_order":0},{"source":"Other tasks","id_source":"9997","target":"classifier","id_target":"55","weight":15.6,"id_order":0},{"source":"Other tasks","id_source":"9997","target":"language technologies","id_target":"56","weight":12.0,"id_order":0},{"source":"Other tasks","id_source":"9997","target":"lstm","id_target":"57","weight":18.2,"id_order":0},{"source":"Other tasks","id_source":"9997","target":"word embeddings","id_target":"58","weight":22.4,"id_order":0},{"source":"Other tasks","id_source":"9997","target":"ensemble approach","id_target":"59","weight":10.1,"id_order":0},{"source":"No Poverty","id_source":"0","target":"Other tasks","id_target":"9997","weight":14.0,"id_order":9999},{"source":"No Hunger","id_source":"1","target":"Other tasks","id_target":"9997","weight":2.8,"id_order":9999},{"source":"Good Health and Well-Being","id_source":"2","target":"Other tasks","id_target":"9997","weight":23.4,"id_order":9999},{"source":"Quality Education","id_source":"3","target":"Other tasks","id_target":"9997","weight":30.3,"id_order":9999},{"source":"Gender Equality","id_source":"4","target":"Other tasks","id_target":"9997","weight":119.8,"id_order":9999},{"source":"Clean Water and Sanitation","id_source":"5","target":"Other tasks","id_target":"9997","weight":5.2,"id_order":9999},{"source":"Affordable and Clean Energy","id_source":"6","target":"Other tasks","id_target":"9997","weight":1.5,"id_order":9999},{"source":"Decent Work and Economic Growth","id_source":"7","target":"Other tasks","id_target":"9997","weight":6.5,"id_order":9999},{"source":"Industry, Innovation and Infrastrucure","id_source":"8","target":"Other tasks","id_target":"9997","weight":3.2,"id_order":9999},{"source":"Reduced Inequalities","id_source":"9","target":"Other tasks","id_target":"9997","weight":53.1,"id_order":9999},{"source":"Sustainable Cities and Communities","id_source":"10","target":"Other tasks","id_target":"9997","weight":34.5,"id_order":9999},{"source":"Responsible Consumption and Production","id_source":"11","target":"Other tasks","id_target":"9997","weight":1.4,"id_order":9999},{"source":"Climate Action","id_source":"12","target":"Other tasks","id_target":"9997","weight":162.2,"id_order":9999},{"source":"Life Below Water","id_source":"13","target":"Other tasks","id_target":"9997","weight":19.0,"id_order":9999},{"source":"Life on Land","id_source":"14","target":"Other tasks","id_target":"9997","weight":35.0,"id_order":9999},{"source":"Peace, Justice and Strong Institutions","id_source":"15","target":"Other tasks","id_target":"9997","weight":20.2,"id_order":9999},{"source":"Partnership for the Goals","id_source":"16","target":"Other tasks","id_target":"9997","weight":15.9,"id_order":9999},{"source":"Other","id_source":"17","target":"Other tasks","id_target":"9997","weight":7.8,"id_order":9999},{"source":"covid 19","id_source":"18","target":"Other methods","id_target":"9998","weight":52.2,"id_order":9999},{"source":"hate speech detection","id_source":"19","target":"Other methods","id_target":"9998","weight":22.8,"id_order":9999},{"source":"hope speech detection","id_source":"20","target":"Other methods","id_target":"9998","weight":16.3,"id_order":9999},{"source":"machine translation","id_source":"21","target":"Other methods","id_target":"9998","weight":342.8,"id_order":9999},{"source":"named entity recognition","id_source":"22","target":"Other methods","id_target":"9998","weight":93.8,"id_order":9999},{"source":"nlp tasks","id_source":"23","target":"Other methods","id_target":"9998","weight":18.3,"id_order":9999},{"source":"offensive language identification","id_source":"24","target":"Other methods","id_target":"9998","weight":22.7,"id_order":9999},{"source":"parsing","id_source":"25","target":"Other methods","id_target":"9998","weight":29.3,"id_order":9999},{"source":"sentiment analysis","id_source":"26","target":"Other methods","id_target":"9998","weight":44.2,"id_order":9999},{"source":"summarization","id_source":"27","target":"Other methods","id_target":"9998","weight":46.5,"id_order":9999},{"source":"text classification","id_source":"28","target":"Other methods","id_target":"9998","weight":27.1,"id_order":9999},{"source":"classification","id_source":"29","target":"Other methods","id_target":"9998","weight":90.4,"id_order":9999},{"source":"automatic speech recognition","id_source":"30","target":"Other methods","id_target":"9998","weight":30.7,"id_order":9999},{"source":"annotation","id_source":"32","target":"Other methods","id_target":"9998","weight":48.3,"id_order":9999},{"source":"emotion detection","id_source":"33","target":"Other methods","id_target":"9998","weight":24.5,"id_order":9999},{"source":"fake news detection","id_source":"34","target":"Other methods","id_target":"9998","weight":20.8,"id_order":9999},{"source":"question answering","id_source":"35","target":"Other methods","id_target":"9998","weight":22.7,"id_order":9999},{"source":"relation extraction","id_source":"36","target":"Other methods","id_target":"9998","weight":21.3,"id_order":9999},{"source":"offensive language detection","id_source":"37","target":"Other methods","id_target":"9998","weight":18.2,"id_order":9999},{"source":"emotion recognition","id_source":"38","target":"Other methods","id_target":"9998","weight":24.1,"id_order":9999}]